{
	"$schema": "https://raw.githubusercontent.com/edave64/doki-doki-dialog-generator-pack-format/master/src/v1/schema.json",
	"id": "ddlc.oc.mio",
	"packId": "mio.outfits.dress.blackrabbitartworks.edave64",
	"name": "Mio",
	"folder": "./",
	"styles": [
		{
			"name": "blackrabbitartworks_dress",
			"label": "Dress"
		}
	],
	"poses": [
		{
			"name": "blackrabbitartworks_dress_normal",
			"style": "blackrabbitartworks_dress",
			"compatibleHeads": ["default"],
			"variant": [
				"1.png",
				"2.png",
				"3.png",
				"4.png",
				"5.png",
				"6.png",
				"7.png",
				"8.png"
			]
		}
	]
}
